conference_scheduler_cli-0.10.1.dist-info/DESCRIPTION.rst
conference_scheduler_cli-0.10.1.dist-info/METADATA
conference_scheduler_cli-0.10.1.dist-info/RECORD
conference_scheduler_cli-0.10.1.dist-info/WHEEL
conference_scheduler_cli-0.10.1.dist-info/entry_points.txt
conference_scheduler_cli-0.10.1.dist-info/metadata.json
conference_scheduler_cli-0.10.1.dist-info/top_level.txt
scheduler/__init__.py
scheduler/__main__.py
scheduler/calculate.py
scheduler/cli.py
scheduler/convert.py
scheduler/decorators.py
scheduler/define.py
scheduler/denormalise.py
scheduler/io.py
scheduler/logging.py
scheduler/session.py
