Metadata-Version: 2.0
Name: conference-scheduler-cli
Version: 0.10.1
Summary: A command line tool to manage the schedule for a conference
Home-page: https://github.com/pyconuk/conferencescheduler-cli
Author: The UK Python Association
Author-email: owen.campbell@uk.python.org
License: MIT license
Platform: UNKNOWN
Classifier: Intended Audience :: Developers
Classifier: License :: OSI Approved :: MIT License
Classifier: Operating System :: Unix
Classifier: Operating System :: POSIX
Classifier: Programming Language :: Python
Classifier: Programming Language :: Python :: 3.6
Classifier: Programming Language :: Python :: Implementation :: CPython
Classifier: Topic :: Utilities
Requires-Python: >=3.6
Requires-Dist: click (>=6.7)
Requires-Dist: conference-scheduler (>=2.1.2)
Requires-Dist: daiquiri (>=1.2.1)
Requires-Dist: python-slugify (>=1.2.4)
Requires-Dist: ruamel.yaml (>=0.15.23)
